<?xml version="1.0" encoding="utf-8"?>
<struct>
    <int hash="djc_leniency_frame">6</int>
    <float hash="meter_max_damage">300</float>
    <int hash="meter_level_count">10</int>
    <int hash="meter_flash_frame_count">120</int>
    <struct hash="ecb_group_shift_amount">
        <float hash="small">2</float>
        <float hash="medium">3.5</float>
        <float hash="large">4</float>
        <float hash="x_large">5</float>
        <float hash="xx_large">6</float>
    </struct>
    <int hash="ecb_shift_air_trans_frame">10</int>
    <float hash="ecb_shift_for_waveland">-0.2</float>
    <float hash="general_flick_y_sens">-0.66</float>
    <struct hash="drift_di">
        <float hash="speed_mul_base">0.005</float>
        <float hash="speed_mul_add_max">0.008</float>
        <float hash="speed_lerp_min">0.35</float>
        <float hash="speed_lerp_max">2</float>
    </struct>
    <float hash="glide_toss_cancel_frame">6</float>
    <float hash="waveland_pass_neutral_sens">-0.3</float>
    <int hash="air_escape_snap_frame">5</int>
    <float hash="waveland_distance_threshold">6</float>
    
</struct>